jupyterlab_data_explorer/__init__.py
jupyterlab_data_explorer/_version.py
jupyterlab_data_explorer/comments.py
jupyterlab_data_explorer/comments_db.py
jupyterlab_data_explorer/const.py
jupyterlab_data_explorer/db.py
jupyterlab_data_explorer/engine.py
jupyterlab_data_explorer/handlers.py
jupyterlab_data_explorer/serializer.py
jupyterlab_data_explorer/task.py
jupyterlab_data_explorer/labextension/package.json
jupyterlab_data_explorer/labextension/schemas/jupyterlab-data-explorer/package.json.orig
jupyterlab_data_explorer/labextension/schemas/jupyterlab-data-explorer/plugin.json
jupyterlab_data_explorer/labextension/static/491.5d64fe9fa81b768fd9ff.js
jupyterlab_data_explorer/labextension/static/591.27cd931e59d9e286c798.js
jupyterlab_data_explorer/labextension/static/672.e84b720734ebf6cb1e6b.js
jupyterlab_data_explorer/labextension/static/713.d169e0543fafdd10e21f.js
jupyterlab_data_explorer/labextension/static/722.9b8182a23845de4eec92.js
jupyterlab_data_explorer/labextension/static/728.e13290b2348d3d9d9a61.js
jupyterlab_data_explorer/labextension/static/94.01a0c4ae005deb5a65de.js
jupyterlab_data_explorer/labextension/static/remoteEntry.65ea0ab63973ebcaba70.js
jupyterlab_data_explorer/labextension/static/style.js
jupyterlab_data_explorer/labextension/static/third-party-licenses.json
jupyterlab_data_explorer/tests/__init__.py
jupyterlab_data_explorer/tests/test_comments.py
jupyterlab_data_explorer/tests/test_handlers.py
jupyterlab_data_explorer/tests/test_sqlite.py
jupyterlab_data_explorer/tests/test_utils.py
jupyterlab_data_explorer-0.0.2.data/data/etc/jupyter/jupyter_notebook_config.d/jupyterlab-data-explorer.json
jupyterlab_data_explorer-0.0.2.data/data/etc/jupyter/jupyter_server_config.d/jupyterlab-data-explorer.json
jupyterlab_data_explorer-0.0.2.data/data/share/jupyter/labextensions/jupyterlab-data-explorer/package.json
jupyterlab_data_explorer-0.0.2.data/data/share/jupyter/labextensions/jupyterlab-data-explorer/schemas/jupyterlab-data-explorer/package.json.orig
jupyterlab_data_explorer-0.0.2.dist-info/METADATA
jupyterlab_data_explorer-0.0.2.dist-info/WHEEL
jupyterlab_data_explorer-0.0.2.dist-info/licenses/LICENSE
jupyterlab_data_explorer-0.0.2.dist-info/RECORD
