Metadata-Version: 2.3
Name: jupyterlab-data-explorer
Version: 0.0.2
Dynamic: Keywords
Summary: A JupyterLab extension for Database
Project-URL: Homepage, https://github.com/groupnotes/jupyterlab-data-explorer
Project-URL: Bug Tracker, https://github.com/groupnotes/jupyterlab-data-explorer/issues
Project-URL: Repository, https://github.com/groupnotes/jupyterlab-data-explorer.git
Author: yannanjing
License: BSD 3-Clause License
License-File: LICENSE
Classifier: Framework :: Jupyter
Classifier: Framework :: Jupyter :: JupyterLab
Classifier: Framework :: Jupyter :: JupyterLab :: 4
Classifier: Framework :: Jupyter :: JupyterLab :: Extensions
Classifier: Framework :: Jupyter :: JupyterLab :: Extensions :: Prebuilt
Classifier: License :: OSI Approved :: BSD License
Classifier: Programming Language :: Python
Classifier: Programming Language :: Python :: 3
Classifier: Programming Language :: Python :: 3.8
Classifier: Programming Language :: Python :: 3.9
Classifier: Programming Language :: Python :: 3.10
Classifier: Programming Language :: Python :: 3.11
Classifier: Programming Language :: Python :: 3.12
Requires-Python: >=3.8
Requires-Dist: jupyter-server<3,>=2.0.1
Requires-Dist: sqlalchemy>=1.3
Requires-Dist: sqlparse>=0.4.1
Provides-Extra: hive
Requires-Dist: pyhive[hive]>=0.6.5; extra == 'hive'
Provides-Extra: mysql
Requires-Dist: pymysql; extra == 'mysql'
Provides-Extra: pgsql
Requires-Dist: psycopg2; extra == 'pgsql'
Provides-Extra: test
Requires-Dist: coverage; extra == 'test'
Requires-Dist: pytest; extra == 'test'
Requires-Dist: pytest-asyncio; extra == 'test'
Requires-Dist: pytest-cov; extra == 'test'
Requires-Dist: pytest-jupyter[server]>=0.6.0; extra == 'test'
